classifier/__init__.py
classifier/main.py
Data_Sciene-0.0.1.dist-info/METADATA
Data_Sciene-0.0.1.dist-info/WHEEL
Data_Sciene-0.0.1.dist-info/top_level.txt
Data_Sciene-0.0.1.dist-info/RECORD
