Metadata-Version: 2.1
Name: Data-Sciene
Version: 0.0.1
Summary: Classifing library.
Author: Your Name
Author-email: your.email@example.com
Keywords: dataminds classifier
Classifier: Development Status :: 5 - Production/Stable
Classifier: Intended Audience :: Developers
Classifier: Topic :: Software Development :: Libraries
Classifier: License :: OSI Approved :: MIT License
Classifier: Programming Language :: Python :: 3
Classifier: Programming Language :: Python :: 3.6
Classifier: Programming Language :: Python :: 3.7
Classifier: Programming Language :: Python :: 3.8
Requires-Python: >=3.6
